automation_engine/__init__.py
automation_engine/config.py
automation_engine/engine.py
automation_engine/mqtt/__init__.py
automation_engine/mqtt/topic.py
automation_engine/mqtt/wrapper.py
automation_engine/piston.py
automation_engine/plugins/__init__.py
automation_engine/plugins/hue.py
automation_engine/plugins/plugin.py
automation_engine/plugins/state.py
automation_engine/py.typed
automation_engine/version.py
automation_engine-0.5.0.dist-info/LICENSE
automation_engine-0.5.0.dist-info/WHEEL
automation_engine-0.5.0.dist-info/METADATA
automation_engine-0.5.0.dist-info/RECORD
