Metadata-Version: 2.1
Name: automation-engine
Version: 0.5.0
Summary: Automation Engine powered by MQTT
Home-page: https://github.com/trickeydan/automation-engine
License: MIT
Author: Dan Trickey
Author-email: contact@trickey.io
Requires-Python: >=3.8,<4.0
Classifier: License :: OSI Approved :: MIT License
Classifier: Programming Language :: Python :: 3
Classifier: Programming Language :: Python :: 3.10
Classifier: Programming Language :: Python :: 3.8
Classifier: Programming Language :: Python :: 3.9
Classifier: Topic :: Software Development :: Libraries :: Python Modules
Classifier: Typing :: Typed
Provides-Extra: all
Provides-Extra: hue
Requires-Dist: gmqtt (>=0.6.10,<0.7.0)
Requires-Dist: hue2mqtt (>=0.4.0,<0.5.0); extra == "all" or extra == "hue"
Requires-Dist: prometheus-client (>=0.14.1,<0.15.0)
Requires-Dist: pydantic (>=1.9.2,<2.0.0)
Requires-Dist: tomli (>=2.0.1,<3.0.0); python_version <= "3.10"
Project-URL: Documentation, https://github.com/trickeydan/automation-engine
Project-URL: Repository, https://github.com/trickeydan/automation-engine
